CHANGELOG.txt
LICENSE.txt
MANIFEST.in
README.txt
setup.py
SteamPyKey.egg-info/PKG-INFO
SteamPyKey.egg-info/SOURCES.txt
SteamPyKey.egg-info/dependency_links.txt
SteamPyKey.egg-info/top_level.txt
SteamPyKey3/__init__.py